{"title": "🎁 Получай @Podarok_9 за отправку стикеров", "id": "tg-7628409135175827415", "net.maunium.telegram.pack": {"short_name": "myttcore", "hash": "-30051821"}, "stickers": [{"body": "🤙", "url": "mxc://matrix.gubanov.site/ZFiRuZEq2VTi5IxQVmmqZqsnc1vhUjUE", "info": {"w": 256, "h": 256, "size": 44194, "mimetype": "image/gif", "thumbnail_url": "mxc://matrix.gubanov.site/ZFiRuZEq2VTi5IxQVmmqZqsnc1vhUjUE", "thumbnail_info": {"w": 256, "h": 256, "size": 44194, "mimetype": "image/gif"}}, "msgtype": "m.sticker", "id": "tg-5222204508473425673", "net.maunium.telegram.sticker": {"pack": {"id": "7628409135175827415", "short_name": "myttcore"}, "id": "5222204508473425673", "emoticons": ["🤙"]}}, {"body": "😝", "url": "mxc://matrix.gubanov.site/eShiaKrIy9kp3ccyTOkxAhp57yiJnwOm", "info": {"w": 256, "h": 256, "size": 2408976, "mimetype": "image/gif", "thumbnail_url": "mxc://matrix.gubanov.site/eShiaKrIy9kp3ccyTOkxAhp57yiJnwOm", "thumbnail_info": {"w": 256, "h": 256, "size": 2408976, "mimetype": "image/gif"}}, "msgtype": "m.sticker", "id": "tg-5386643391599642908", "net.maunium.telegram.sticker": {"pack": {"id": "7628409135175827415", "short_name": "myttcore"}, "id": "5386643391599642908", "emoticons": ["😝"]}}, {"body": "⬆️", "url": "mxc://matrix.gubanov.site/RbGF02emqfAlzFiYLVLhg0FjFhNOtC2V", "info": {"w": 256, "h": 256, "size": 25660, "mimetype": "image/gif", "thumbnail_url": "mxc://matrix.gubanov.site/RbGF02emqfAlzFiYLVLhg0FjFhNOtC2V", "thumbnail_info": {"w": 256, "h": 256, "size": 25660, "mimetype": "image/gif"}}, "msgtype": "m.sticker", "id": "tg-5296396224516101010", "net.maunium.telegram.sticker": {"pack": {"id": "7628409135175827415", "short_name": "myttcore"}, "id": "5296396224516101010", "emoticons": ["⬆"]}}, {"body": "🤨", "url": "mxc://matrix.gubanov.site/6KXcE2xxIEQl43jEnfwdVZAjT5Icx8HN", "info": {"w": 256, "h": 256, "size": 1837316, "mimetype": "image/gif", "thumbnail_url": "mxc://matrix.gubanov.site/6KXcE2xxIEQl43jEnfwdVZAjT5Icx8HN", "thumbnail_info": {"w": 256, "h": 256, "size": 1837316, "mimetype": "image/gif"}}, "msgtype": "m.sticker", "id": "tg-5231066743991997275", "net.maunium.telegram.sticker": {"pack": {"id": "7628409135175827415", "short_name": "myttcore"}, "id": "5231066743991997275", "emoticons": ["🤨"]}}, {"body": "😝", "url": "mxc://matrix.gubanov.site/H4CdFaxTz73LtzCIeN5fmiVbbQjv3yx1", "info": {"w": 256, "h": 256, "size": 2014757, "mimetype": "image/gif", "thumbnail_url": "mxc://matrix.gubanov.site/H4CdFaxTz73LtzCIeN5fmiVbbQjv3yx1", "thumbnail_info": {"w": 256, "h": 256, "size": 2014757, "mimetype": "image/gif"}}, "msgtype": "m.sticker", "id": "tg-5395664837260901099", "net.maunium.telegram.sticker": {"pack": {"id": "7628409135175827415", "short_name": "myttcore"}, "id": "5395664837260901099", "emoticons": ["😝"]}}, {"body": "😜", "url": "mxc://matrix.gubanov.site/IZ30JHlivjOAmWJ0OVltbIFrZEbcTkRn", "info": {"w": 256, "h": 256, "size": 4856222, "mimetype": "image/gif", "thumbnail_url": "mxc://matrix.gubanov.site/IZ30JHlivjOAmWJ0OVltbIFrZEbcTkRn", "thumbnail_info": {"w": 256, "h": 256, "size": 4856222, "mimetype": "image/gif"}}, "msgtype": "m.sticker", "id": "tg-5231241463261597522", "net.maunium.telegram.sticker": {"pack": {"id": "7628409135175827415", "short_name": "myttcore"}, "id": "5231241463261597522", "emoticons": ["😜"]}}, {"body": "😜", "url": "mxc://matrix.gubanov.site/QSF6CD2sxwd8vVjxDnIyGg9ZCt2vfDoO", "info": {"w": 256, "h": 256, "size": 856448, "mimetype": "image/gif", "thumbnail_url": "mxc://matrix.gubanov.site/QSF6CD2sxwd8vVjxDnIyGg9ZCt2vfDoO", "thumbnail_info": {"w": 256, "h": 256, "size": 856448, "mimetype": "image/gif"}}, "msgtype": "m.sticker", "id": "tg-5406721831132496840", "net.maunium.telegram.sticker": {"pack": {"id": "7628409135175827415", "short_name": "myttcore"}, "id": "5406721831132496840", "emoticons": ["😜"]}}, {"body": "🤦‍♂️", "url": "mxc://matrix.gubanov.site/XsxjUxwntgA3V7r3ygJOwEba3W8kmHw0", "info": {"w": 256, "h": 256, "size": 2619421, "mimetype": "image/gif", "thumbnail_url": "mxc://matrix.gubanov.site/XsxjUxwntgA3V7r3ygJOwEba3W8kmHw0", "thumbnail_info": {"w": 256, "h": 256, "size": 2619421, "mimetype": "image/gif"}}, "msgtype": "m.sticker", "id": "tg-5249084784633744844", "net.maunium.telegram.sticker": {"pack": {"id": "7628409135175827415", "short_name": "myttcore"}, "id": "5249084784633744844", "emoticons": ["🤦‍♂"]}}, {"body": "😆", "url": "mxc://matrix.gubanov.site/dTQPLOMlQS0irpUqc7961nDpDVjokrJV", "info": {"w": 256, "h": 256, "size": 1512090, "mimetype": "image/gif", "thumbnail_url": "mxc://matrix.gubanov.site/dTQPLOMlQS0irpUqc7961nDpDVjokrJV", "thumbnail_info": {"w": 256, "h": 256, "size": 1512090, "mimetype": "image/gif"}}, "msgtype": "m.sticker", "id": "tg-5395351016885491843", "net.maunium.telegram.sticker": {"pack": {"id": "7628409135175827415", "short_name": "myttcore"}, "id": "5395351016885491843", "emoticons": ["😆"]}}, {"body": "🕊", "url": "mxc://matrix.gubanov.site/V4ckdEQF7hYVzvSmcduonWS7VhjZeiY0", "info": {"w": 256, "h": 256, "size": 5225444, "mimetype": "image/gif", "thumbnail_url": "mxc://matrix.gubanov.site/V4ckdEQF7hYVzvSmcduonWS7VhjZeiY0", "thumbnail_info": {"w": 256, "h": 256, "size": 5225444, "mimetype": "image/gif"}}, "msgtype": "m.sticker", "id": "tg-5298643411534910575", "net.maunium.telegram.sticker": {"pack": {"id": "7628409135175827415", "short_name": "myttcore"}, "id": "5298643411534910575", "emoticons": ["🕊"]}}, {"body": "🥹", "url": "mxc://matrix.gubanov.site/grhsTGuIUmM3cFU7kbOaOeJLd2Mu1k18", "info": {"w": 256, "h": 256, "size": 1355091, "mimetype": "image/gif", "thumbnail_url": "mxc://matrix.gubanov.site/grhsTGuIUmM3cFU7kbOaOeJLd2Mu1k18", "thumbnail_info": {"w": 256, "h": 256, "size": 1355091, "mimetype": "image/gif"}}, "msgtype": "m.sticker", "id": "tg-5249242525897626844", "net.maunium.telegram.sticker": {"pack": {"id": "7628409135175827415", "short_name": "myttcore"}, "id": "5249242525897626844", "emoticons": ["🥹"]}}, {"body": "🍓", "url": "mxc://matrix.gubanov.site/RQwwQSFPwEHw7zsgMHqlv0Oom59d6Inh", "info": {"w": 256, "h": 256, "size": 3128757, "mimetype": "image/gif", "thumbnail_url": "mxc://matrix.gubanov.site/RQwwQSFPwEHw7zsgMHqlv0Oom59d6Inh", "thumbnail_info": {"w": 256, "h": 256, "size": 3128757, "mimetype": "image/gif"}}, "msgtype": "m.sticker", "id": "tg-5300949645764104234", "net.maunium.telegram.sticker": {"pack": {"id": "7628409135175827415", "short_name": "myttcore"}, "id": "5300949645764104234", "emoticons": ["🍓"]}}, {"body": "😤", "url": "mxc://matrix.gubanov.site/pRq0B9fFlPrCjWURRLLyZ6FKLMNsXYwE", "info": {"w": 256, "h": 256, "size": 2984250, "mimetype": "image/gif", "thumbnail_url": "mxc://matrix.gubanov.site/pRq0B9fFlPrCjWURRLLyZ6FKLMNsXYwE", "thumbnail_info": {"w": 256, "h": 256, "size": 2984250, "mimetype": "image/gif"}}, "msgtype": "m.sticker", "id": "tg-5301287530841282489", "net.maunium.telegram.sticker": {"pack": {"id": "7628409135175827415", "short_name": "myttcore"}, "id": "5301287530841282489", "emoticons": ["😤"]}}, {"body": "😛", "url": "mxc://matrix.gubanov.site/KjlT776JrCIooQGcj9RRTMV8Jj3lhbF0", "info": {"w": 256, "h": 256, "size": 4877100, "mimetype": "image/gif", "thumbnail_url": "mxc://matrix.gubanov.site/KjlT776JrCIooQGcj9RRTMV8Jj3lhbF0", "thumbnail_info": {"w": 256, "h": 256, "size": 4877100, "mimetype": "image/gif"}}, "msgtype": "m.sticker", "id": "tg-5231183038821469561", "net.maunium.telegram.sticker": {"pack": {"id": "7628409135175827415", "short_name": "myttcore"}, "id": "5231183038821469561", "emoticons": ["😛"]}}, {"body": "😝", "url": "mxc://matrix.gubanov.site/pfgzDdrLUCcfNETHHMY2KkfWSNplc0Np", "info": {"w": 256, "h": 256, "size": 853883, "mimetype": "image/gif", "thumbnail_url": "mxc://matrix.gubanov.site/pfgzDdrLUCcfNETHHMY2KkfWSNplc0Np", "thumbnail_info": {"w": 256, "h": 256, "size": 853883, "mimetype": "image/gif"}}, "msgtype": "m.sticker", "id": "tg-5386403294337864752", "net.maunium.telegram.sticker": {"pack": {"id": "7628409135175827415", "short_name": "myttcore"}, "id": "5386403294337864752", "emoticons": ["😝"]}}, {"body": "🙂", "url": "mxc://matrix.gubanov.site/kbsWHwehzTiCCm0A7Y4oy7YeUqRpSRMy", "info": {"w": 256, "h": 256, "size": 2544975, "mimetype": "image/gif", "thumbnail_url": "mxc://matrix.gubanov.site/kbsWHwehzTiCCm0A7Y4oy7YeUqRpSRMy", "thumbnail_info": {"w": 256, "h": 256, "size": 2544975, "mimetype": "image/gif"}}, "msgtype": "m.sticker", "id": "tg-5249145588485756645", "net.maunium.telegram.sticker": {"pack": {"id": "7628409135175827415", "short_name": "myttcore"}, "id": "5249145588485756645", "emoticons": ["🙂"]}}, {"body": "👍", "url": "mxc://matrix.gubanov.site/BGtX3kSY2uCBFIsk52mS3OxsTNcBXSa5", "info": {"w": 256, "h": 256, "size": 1432861, "mimetype": "image/gif", "thumbnail_url": "mxc://matrix.gubanov.site/BGtX3kSY2uCBFIsk52mS3OxsTNcBXSa5", "thumbnail_info": {"w": 256, "h": 256, "size": 1432861, "mimetype": "image/gif"}}, "msgtype": "m.sticker", "id": "tg-5406947995520365529", "net.maunium.telegram.sticker": {"pack": {"id": "7628409135175827415", "short_name": "myttcore"}, "id": "5406947995520365529", "emoticons": ["👍"]}}, {"body": "🌧", "url": "mxc://matrix.gubanov.site/OtQG4TXFHax9MglL3tcoxDz8mHeIkMl8", "info": {"w": 256, "h": 256, "size": 1609689, "mimetype": "image/gif", "thumbnail_url": "mxc://matrix.gubanov.site/OtQG4TXFHax9MglL3tcoxDz8mHeIkMl8", "thumbnail_info": {"w": 256, "h": 256, "size": 1609689, "mimetype": "image/gif"}}, "msgtype": "m.sticker", "id": "tg-5406901635643374387", "net.maunium.telegram.sticker": {"pack": {"id": "7628409135175827415", "short_name": "myttcore"}, "id": "5406901635643374387", "emoticons": ["🌧"]}}, {"body": "🚿", "url": "mxc://matrix.gubanov.site/7ltQkUytL4U6NZ9ZB5aBgOyimr5Hu1Fd", "info": {"w": 256, "h": 256, "size": 1981566, "mimetype": "image/gif", "thumbnail_url": "mxc://matrix.gubanov.site/7ltQkUytL4U6NZ9ZB5aBgOyimr5Hu1Fd", "thumbnail_info": {"w": 256, "h": 256, "size": 1981566, "mimetype": "image/gif"}}, "msgtype": "m.sticker", "id": "tg-5222112265460812563", "net.maunium.telegram.sticker": {"pack": {"id": "7628409135175827415", "short_name": "myttcore"}, "id": "5222112265460812563", "emoticons": ["🚿"]}}, {"body": "🤨", "url": "mxc://matrix.gubanov.site/e6qc8wQy786E5ue4V10EUyklAJRsUL3V", "info": {"w": 256, "h": 256, "size": 39401, "mimetype": "image/gif", "thumbnail_url": "mxc://matrix.gubanov.site/e6qc8wQy786E5ue4V10EUyklAJRsUL3V", "thumbnail_info": {"w": 256, "h": 256, "size": 39401, "mimetype": "image/gif"}}, "msgtype": "m.sticker", "id": "tg-5267389187924987249", "net.maunium.telegram.sticker": {"pack": {"id": "7628409135175827415", "short_name": "myttcore"}, "id": "5267389187924987249", "emoticons": ["🤨"]}}, {"body": "🍒", "url": "mxc://matrix.gubanov.site/fECukpntQ11HKmMGLK4zIXUeLM01cyzC", "info": {"w": 256, "h": 256, "size": 28908, "mimetype": "image/gif", "thumbnail_url": "mxc://matrix.gubanov.site/fECukpntQ11HKmMGLK4zIXUeLM01cyzC", "thumbnail_info": {"w": 256, "h": 256, "size": 28908, "mimetype": "image/gif"}}, "msgtype": "m.sticker", "id": "tg-5287384442531252909", "net.maunium.telegram.sticker": {"pack": {"id": "7628409135175827415", "short_name": "myttcore"}, "id": "5287384442531252909", "emoticons": ["🍒"]}}, {"body": "🍅", "url": "mxc://matrix.gubanov.site/N5OppMYMJ86sOFF3u0Wx3syy5tlbAMW9", "info": {"w": 256, "h": 256, "size": 27047, "mimetype": "image/gif", "thumbnail_url": "mxc://matrix.gubanov.site/N5OppMYMJ86sOFF3u0Wx3syy5tlbAMW9", "thumbnail_info": {"w": 256, "h": 256, "size": 27047, "mimetype": "image/gif"}}, "msgtype": "m.sticker", "id": "tg-5287373726587852299", "net.maunium.telegram.sticker": {"pack": {"id": "7628409135175827415", "short_name": "myttcore"}, "id": "5287373726587852299", "emoticons": ["🍅"]}}, {"body": "🐱", "url": "mxc://matrix.gubanov.site/2BGy9GYADKZF0PciSetkHdgHNSaK0ki5", "info": {"w": 256, "h": 256, "size": 1184338, "mimetype": "image/gif", "thumbnail_url": "mxc://matrix.gubanov.site/2BGy9GYADKZF0PciSetkHdgHNSaK0ki5", "thumbnail_info": {"w": 256, "h": 256, "size": 1184338, "mimetype": "image/gif"}}, "msgtype": "m.sticker", "id": "tg-5249233656790158379", "net.maunium.telegram.sticker": {"pack": {"id": "7628409135175827415", "short_name": "myttcore"}, "id": "5249233656790158379", "emoticons": ["🐱"]}}, {"body": "🙄", "url": "mxc://matrix.gubanov.site/dz8OwbU0wneTBI5WVM6YHdhEonkurcxt", "info": {"w": 256, "h": 256, "size": 2733817, "mimetype": "image/gif", "thumbnail_url": "mxc://matrix.gubanov.site/dz8OwbU0wneTBI5WVM6YHdhEonkurcxt", "thumbnail_info": {"w": 256, "h": 256, "size": 2733817, "mimetype": "image/gif"}}, "msgtype": "m.sticker", "id": "tg-5249435202425491054", "net.maunium.telegram.sticker": {"pack": {"id": "7628409135175827415", "short_name": "myttcore"}, "id": "5249435202425491054", "emoticons": ["🙄"]}}, {"body": "😁", "url": "mxc://matrix.gubanov.site/ce64iKMpSbjWVcot4UUmZn4EgMmnlS65", "info": {"w": 256, "h": 256, "size": 6588667, "mimetype": "image/gif", "thumbnail_url": "mxc://matrix.gubanov.site/ce64iKMpSbjWVcot4UUmZn4EgMmnlS65", "thumbnail_info": {"w": 256, "h": 256, "size": 6588667, "mimetype": "image/gif"}}, "msgtype": "m.sticker", "id": "tg-5361625842755595666", "net.maunium.telegram.sticker": {"pack": {"id": "7628409135175827415", "short_name": "myttcore"}, "id": "5361625842755595666", "emoticons": ["😁"]}}, {"body": "😆", "url": "mxc://matrix.gubanov.site/oT6dTKcWbQgQrKHwV0LSbFKUcryE0JOn", "info": {"w": 256, "h": 256, "size": 1735589, "mimetype": "image/gif", "thumbnail_url": "mxc://matrix.gubanov.site/oT6dTKcWbQgQrKHwV0LSbFKUcryE0JOn", "thumbnail_info": {"w": 256, "h": 256, "size": 1735589, "mimetype": "image/gif"}}, "msgtype": "m.sticker", "id": "tg-5229040434256315572", "net.maunium.telegram.sticker": {"pack": {"id": "7628409135175827415", "short_name": "myttcore"}, "id": "5229040434256315572", "emoticons": ["😆"]}}, {"body": "😡", "url": "mxc://matrix.gubanov.site/oycCfXL3ccTYodeMphA8tYpJoOL7JHfV", "info": {"w": 256, "h": 256, "size": 1779445, "mimetype": "image/gif", "thumbnail_url": "mxc://matrix.gubanov.site/oycCfXL3ccTYodeMphA8tYpJoOL7JHfV", "thumbnail_info": {"w": 256, "h": 256, "size": 1779445, "mimetype": "image/gif"}}, "msgtype": "m.sticker", "id": "tg-5445018040171270869", "net.maunium.telegram.sticker": {"pack": {"id": "7628409135175827415", "short_name": "myttcore"}, "id": "5445018040171270869", "emoticons": ["😡"]}}, {"body": "🤨", "url": "mxc://matrix.gubanov.site/kV05uGyWf8ThbGRv3OXlSinPIJLikZzP", "info": {"w": 256, "h": 256, "size": 44270, "mimetype": "image/gif", "thumbnail_url": "mxc://matrix.gubanov.site/kV05uGyWf8ThbGRv3OXlSinPIJLikZzP", "thumbnail_info": {"w": 256, "h": 256, "size": 44270, "mimetype": "image/gif"}}, "msgtype": "m.sticker", "id": "tg-5267124312996879100", "net.maunium.telegram.sticker": {"pack": {"id": "7628409135175827415", "short_name": "myttcore"}, "id": "5267124312996879100", "emoticons": ["🤨"]}}, {"body": "😼", "url": "mxc://matrix.gubanov.site/HKC76O0uwydn6qCc04cFsqmKSHu8cUK3", "info": {"w": 256, "h": 256, "size": 3416249, "mimetype": "image/gif", "thumbnail_url": "mxc://matrix.gubanov.site/HKC76O0uwydn6qCc04cFsqmKSHu8cUK3", "thumbnail_info": {"w": 256, "h": 256, "size": 3416249, "mimetype": "image/gif"}}, "msgtype": "m.sticker", "id": "tg-5343929241761252857", "net.maunium.telegram.sticker": {"pack": {"id": "7628409135175827415", "short_name": "myttcore"}, "id": "5343929241761252857", "emoticons": ["😼"]}}, {"body": "😼", "url": "mxc://matrix.gubanov.site/LkogCsDGpFA3dE9koJ7lGsDcAazKTQUu", "info": {"w": 256, "h": 256, "size": 2981589, "mimetype": "image/gif", "thumbnail_url": "mxc://matrix.gubanov.site/LkogCsDGpFA3dE9koJ7lGsDcAazKTQUu", "thumbnail_info": {"w": 256, "h": 256, "size": 2981589, "mimetype": "image/gif"}}, "msgtype": "m.sticker", "id": "tg-5386431065596398848", "net.maunium.telegram.sticker": {"pack": {"id": "7628409135175827415", "short_name": "myttcore"}, "id": "5386431065596398848", "emoticons": ["😼"]}}, {"body": "🤙", "url": "mxc://matrix.gubanov.site/RTkup71ZKUE9GwOUufb2HeiPTZkz4RFs", "info": {"w": 256, "h": 256, "size": 56745, "mimetype": "image/gif", "thumbnail_url": "mxc://matrix.gubanov.site/RTkup71ZKUE9GwOUufb2HeiPTZkz4RFs", "thumbnail_info": {"w": 256, "h": 256, "size": 56745, "mimetype": "image/gif"}}, "msgtype": "m.sticker", "id": "tg-5343691334932792814", "net.maunium.telegram.sticker": {"pack": {"id": "7628409135175827415", "short_name": "myttcore"}, "id": "5343691334932792814", "emoticons": ["🤙"]}}, {"body": "🤪", "url": "mxc://matrix.gubanov.site/4jZrNjKRLZhiUiqR9BD0UuHjknsmFeuN", "info": {"w": 256, "h": 256, "size": 2425716, "mimetype": "image/gif", "thumbnail_url": "mxc://matrix.gubanov.site/4jZrNjKRLZhiUiqR9BD0UuHjknsmFeuN", "thumbnail_info": {"w": 256, "h": 256, "size": 2425716, "mimetype": "image/gif"}}, "msgtype": "m.sticker", "id": "tg-5344049449305935172", "net.maunium.telegram.sticker": {"pack": {"id": "7628409135175827415", "short_name": "myttcore"}, "id": "5344049449305935172", "emoticons": ["🤪"]}}, {"body": "😜", "url": "mxc://matrix.gubanov.site/IbHrDyfZNcWWrXbt7bUjz2vP4aawPaQt", "info": {"w": 256, "h": 256, "size": 5936165, "mimetype": "image/gif", "thumbnail_url": "mxc://matrix.gubanov.site/IbHrDyfZNcWWrXbt7bUjz2vP4aawPaQt", "thumbnail_info": {"w": 256, "h": 256, "size": 5936165, "mimetype": "image/gif"}}, "msgtype": "m.sticker", "id": "tg-5344082018042940085", "net.maunium.telegram.sticker": {"pack": {"id": "7628409135175827415", "short_name": "myttcore"}, "id": "5344082018042940085", "emoticons": ["😜"]}}, {"body": "🦭", "url": "mxc://matrix.gubanov.site/jlM44BXVE3EjsGeoNAK5CwPgfg0gxSpB", "info": {"w": 256, "h": 256, "size": 4006018, "mimetype": "image/gif", "thumbnail_url": "mxc://matrix.gubanov.site/jlM44BXVE3EjsGeoNAK5CwPgfg0gxSpB", "thumbnail_info": {"w": 256, "h": 256, "size": 4006018, "mimetype": "image/gif"}}, "msgtype": "m.sticker", "id": "tg-5386562147998270293", "net.maunium.telegram.sticker": {"pack": {"id": "7628409135175827415", "short_name": "myttcore"}, "id": "5386562147998270293", "emoticons": ["🦭"]}}, {"body": "🦭", "url": "mxc://matrix.gubanov.site/VL5fdFQH0U8zK0Zhk8pqXYklgSaWIlOb", "info": {"w": 256, "h": 256, "size": 2817411, "mimetype": "image/gif", "thumbnail_url": "mxc://matrix.gubanov.site/VL5fdFQH0U8zK0Zhk8pqXYklgSaWIlOb", "thumbnail_info": {"w": 256, "h": 256, "size": 2817411, "mimetype": "image/gif"}}, "msgtype": "m.sticker", "id": "tg-5386662422599731759", "net.maunium.telegram.sticker": {"pack": {"id": "7628409135175827415", "short_name": "myttcore"}, "id": "5386662422599731759", "emoticons": ["🦭"]}}, {"body": "🦭", "url": "mxc://matrix.gubanov.site/hVn7rROW6rx4PrkhKvwbOMWoIHGkAOFb", "info": {"w": 256, "h": 256, "size": 2323399, "mimetype": "image/gif", "thumbnail_url": "mxc://matrix.gubanov.site/hVn7rROW6rx4PrkhKvwbOMWoIHGkAOFb", "thumbnail_info": {"w": 256, "h": 256, "size": 2323399, "mimetype": "image/gif"}}, "msgtype": "m.sticker", "id": "tg-5386838795431748309", "net.maunium.telegram.sticker": {"pack": {"id": "7628409135175827415", "short_name": "myttcore"}, "id": "5386838795431748309", "emoticons": ["🦭"]}}, {"body": "🦭", "url": "mxc://matrix.gubanov.site/OCmEUXHezkjiduQL7EHnMAFMuyR4Axee", "info": {"w": 256, "h": 256, "size": 2659536, "mimetype": "image/gif", "thumbnail_url": "mxc://matrix.gubanov.site/OCmEUXHezkjiduQL7EHnMAFMuyR4Axee", "thumbnail_info": {"w": 256, "h": 256, "size": 2659536, "mimetype": "image/gif"}}, "msgtype": "m.sticker", "id": "tg-5384187636673976811", "net.maunium.telegram.sticker": {"pack": {"id": "7628409135175827415", "short_name": "myttcore"}, "id": "5384187636673976811", "emoticons": ["🦭"]}}, {"body": "😾", "url": "mxc://matrix.gubanov.site/HmKIggiHz3C8srvK6m4jc7RAoG4WNe3k", "info": {"w": 256, "h": 256, "size": 3989326, "mimetype": "image/gif", "thumbnail_url": "mxc://matrix.gubanov.site/HmKIggiHz3C8srvK6m4jc7RAoG4WNe3k", "thumbnail_info": {"w": 256, "h": 256, "size": 3989326, "mimetype": "image/gif"}}, "msgtype": "m.sticker", "id": "tg-5341504543744103973", "net.maunium.telegram.sticker": {"pack": {"id": "7628409135175827415", "short_name": "myttcore"}, "id": "5341504543744103973", "emoticons": ["😾"]}}, {"body": "🐦‍⬛️", "url": "mxc://matrix.gubanov.site/qiYmNVOP0iTHkhf4rNb04WBSiLNLyW5O", "info": {"w": 256, "h": 256, "size": 41211, "mimetype": "image/gif", "thumbnail_url": "mxc://matrix.gubanov.site/qiYmNVOP0iTHkhf4rNb04WBSiLNLyW5O", "thumbnail_info": {"w": 256, "h": 256, "size": 41211, "mimetype": "image/gif"}}, "msgtype": "m.sticker", "id": "tg-5321060769998083773", "net.maunium.telegram.sticker": {"pack": {"id": "7628409135175827415", "short_name": "myttcore"}, "id": "5321060769998083773", "emoticons": ["🐦‍⬛", "🐦"]}}, {"body": "🐦‍⬛️", "url": "mxc://matrix.gubanov.site/5WyF88kbRmDSb3jR3ZhwysVEW6qyqgJT", "info": {"w": 256, "h": 256, "size": 36582, "mimetype": "image/gif", "thumbnail_url": "mxc://matrix.gubanov.site/5WyF88kbRmDSb3jR3ZhwysVEW6qyqgJT", "thumbnail_info": {"w": 256, "h": 256, "size": 36582, "mimetype": "image/gif"}}, "msgtype": "m.sticker", "id": "tg-5321563796567789032", "net.maunium.telegram.sticker": {"pack": {"id": "7628409135175827415", "short_name": "myttcore"}, "id": "5321563796567789032", "emoticons": ["🐦‍⬛", "🐦"]}}, {"body": "🐦‍⬛️", "url": "mxc://matrix.gubanov.site/5GbUF8uvR5sFSSGplmS2r7ut4E3SqfKf", "info": {"w": 256, "h": 256, "size": 39895, "mimetype": "image/gif", "thumbnail_url": "mxc://matrix.gubanov.site/5GbUF8uvR5sFSSGplmS2r7ut4E3SqfKf", "thumbnail_info": {"w": 256, "h": 256, "size": 39895, "mimetype": "image/gif"}}, "msgtype": "m.sticker", "id": "tg-5319130444191533190", "net.maunium.telegram.sticker": {"pack": {"id": "7628409135175827415", "short_name": "myttcore"}, "id": "5319130444191533190", "emoticons": ["🐦‍⬛", "🐦"]}}, {"body": "🐦‍⬛️", "url": "mxc://matrix.gubanov.site/eFjINpHNikDL7a38PruAU0GlZSMOypsN", "info": {"w": 256, "h": 256, "size": 44423, "mimetype": "image/gif", "thumbnail_url": "mxc://matrix.gubanov.site/eFjINpHNikDL7a38PruAU0GlZSMOypsN", "thumbnail_info": {"w": 256, "h": 256, "size": 44423, "mimetype": "image/gif"}}, "msgtype": "m.sticker", "id": "tg-5321461159734315940", "net.maunium.telegram.sticker": {"pack": {"id": "7628409135175827415", "short_name": "myttcore"}, "id": "5321461159734315940", "emoticons": ["🐦‍⬛", "🐦"]}}, {"body": "🐦‍⬛️", "url": "mxc://matrix.gubanov.site/rYmIQdiekNVLjPjkpaqUWPPzlWmfZApd", "info": {"w": 256, "h": 256, "size": 36595, "mimetype": "image/gif", "thumbnail_url": "mxc://matrix.gubanov.site/rYmIQdiekNVLjPjkpaqUWPPzlWmfZApd", "thumbnail_info": {"w": 256, "h": 256, "size": 36595, "mimetype": "image/gif"}}, "msgtype": "m.sticker", "id": "tg-5321483682542816668", "net.maunium.telegram.sticker": {"pack": {"id": "7628409135175827415", "short_name": "myttcore"}, "id": "5321483682542816668", "emoticons": ["🐦‍⬛", "🐦"]}}, {"body": "🐦‍⬛️", "url": "mxc://matrix.gubanov.site/Fw4z4P4exHsDWeKdNoOHLZz3wjMvG0yU", "info": {"w": 256, "h": 256, "size": 33663, "mimetype": "image/gif", "thumbnail_url": "mxc://matrix.gubanov.site/Fw4z4P4exHsDWeKdNoOHLZz3wjMvG0yU", "thumbnail_info": {"w": 256, "h": 256, "size": 33663, "mimetype": "image/gif"}}, "msgtype": "m.sticker", "id": "tg-5321190894622246958", "net.maunium.telegram.sticker": {"pack": {"id": "7628409135175827415", "short_name": "myttcore"}, "id": "5321190894622246958", "emoticons": ["🐦‍⬛", "🐦"]}}, {"body": "🐦‍⬛️", "url": "mxc://matrix.gubanov.site/PPEv3P74JXjfEsXheeTSw0uailW1Z77m", "info": {"w": 256, "h": 256, "size": 36384, "mimetype": "image/gif", "thumbnail_url": "mxc://matrix.gubanov.site/PPEv3P74JXjfEsXheeTSw0uailW1Z77m", "thumbnail_info": {"w": 256, "h": 256, "size": 36384, "mimetype": "image/gif"}}, "msgtype": "m.sticker", "id": "tg-5321059614651879894", "net.maunium.telegram.sticker": {"pack": {"id": "7628409135175827415", "short_name": "myttcore"}, "id": "5321059614651879894", "emoticons": ["🐦‍⬛", "🐦"]}}, {"body": "🐦‍⬛️", "url": "mxc://matrix.gubanov.site/ugmpEdhthygKWyypP5yJw424LDqTcZpn", "info": {"w": 256, "h": 256, "size": 38791, "mimetype": "image/gif", "thumbnail_url": "mxc://matrix.gubanov.site/ugmpEdhthygKWyypP5yJw424LDqTcZpn", "thumbnail_info": {"w": 256, "h": 256, "size": 38791, "mimetype": "image/gif"}}, "msgtype": "m.sticker", "id": "tg-5319189573006297164", "net.maunium.telegram.sticker": {"pack": {"id": "7628409135175827415", "short_name": "myttcore"}, "id": "5319189573006297164", "emoticons": ["🐦‍⬛", "🐦"]}}, {"body": "🐦‍⬛️", "url": "mxc://matrix.gubanov.site/q2aLCaylq46YrzAV7tkestxLHRSm84rd", "info": {"w": 256, "h": 256, "size": 41434, "mimetype": "image/gif", "thumbnail_url": "mxc://matrix.gubanov.site/q2aLCaylq46YrzAV7tkestxLHRSm84rd", "thumbnail_info": {"w": 256, "h": 256, "size": 41434, "mimetype": "image/gif"}}, "msgtype": "m.sticker", "id": "tg-5318973858273856404", "net.maunium.telegram.sticker": {"pack": {"id": "7628409135175827415", "short_name": "myttcore"}, "id": "5318973858273856404", "emoticons": ["🐦‍⬛", "🐦"]}}, {"body": "😜", "url": "mxc://matrix.gubanov.site/Oe6CaOCrgcIgtDCEupFcl8BSQUwr2t3d", "info": {"w": 256, "h": 256, "size": 2955219, "mimetype": "image/gif", "thumbnail_url": "mxc://matrix.gubanov.site/Oe6CaOCrgcIgtDCEupFcl8BSQUwr2t3d", "thumbnail_info": {"w": 256, "h": 256, "size": 2955219, "mimetype": "image/gif"}}, "msgtype": "m.sticker", "id": "tg-5343637390143557788", "net.maunium.telegram.sticker": {"pack": {"id": "7628409135175827415", "short_name": "myttcore"}, "id": "5343637390143557788", "emoticons": ["😜"]}}, {"body": "😄", "url": "mxc://matrix.gubanov.site/FqhxMoVDTsyiYzuEzFwcIDe4AfHO56rn", "info": {"w": 256, "h": 256, "size": 1804472, "mimetype": "image/gif", "thumbnail_url": "mxc://matrix.gubanov.site/FqhxMoVDTsyiYzuEzFwcIDe4AfHO56rn", "thumbnail_info": {"w": 256, "h": 256, "size": 1804472, "mimetype": "image/gif"}}, "msgtype": "m.sticker", "id": "tg-5228952778268771319", "net.maunium.telegram.sticker": {"pack": {"id": "7628409135175827415", "short_name": "myttcore"}, "id": "5228952778268771319", "emoticons": ["😄"]}}, {"body": "😦", "url": "mxc://matrix.gubanov.site/p3dOKHUJkDjvYZLAugtoUmr5gWId4TbR", "info": {"w": 256, "h": 256, "size": 42930, "mimetype": "image/gif", "thumbnail_url": "mxc://matrix.gubanov.site/p3dOKHUJkDjvYZLAugtoUmr5gWId4TbR", "thumbnail_info": {"w": 256, "h": 256, "size": 42930, "mimetype": "image/gif"}}, "msgtype": "m.sticker", "id": "tg-5235467419023082483", "net.maunium.telegram.sticker": {"pack": {"id": "7628409135175827415", "short_name": "myttcore"}, "id": "5235467419023082483", "emoticons": ["😦"]}}, {"body": "😝", "url": "mxc://matrix.gubanov.site/HCqO81YfwtZisQCAW9UdlRLmLo9BMw9W", "info": {"w": 256, "h": 256, "size": 1956978, "mimetype": "image/gif", "thumbnail_url": "mxc://matrix.gubanov.site/HCqO81YfwtZisQCAW9UdlRLmLo9BMw9W", "thumbnail_info": {"w": 256, "h": 256, "size": 1956978, "mimetype": "image/gif"}}, "msgtype": "m.sticker", "id": "tg-5395494017821608133", "net.maunium.telegram.sticker": {"pack": {"id": "7628409135175827415", "short_name": "myttcore"}, "id": "5395494017821608133", "emoticons": ["😝"]}}, {"body": "👻", "url": "mxc://matrix.gubanov.site/2QGihxvra7kUmMR7L0IcFq7Qb6jn6oob", "info": {"w": 256, "h": 256, "size": 2585744, "mimetype": "image/gif", "thumbnail_url": "mxc://matrix.gubanov.site/2QGihxvra7kUmMR7L0IcFq7Qb6jn6oob", "thumbnail_info": {"w": 256, "h": 256, "size": 2585744, "mimetype": "image/gif"}}, "msgtype": "m.sticker", "id": "tg-5267122839823091084", "net.maunium.telegram.sticker": {"pack": {"id": "7628409135175827415", "short_name": "myttcore"}, "id": "5267122839823091084", "emoticons": ["👻"]}}, {"body": "😝", "url": "mxc://matrix.gubanov.site/cCnKgi1Aze39wnxsKPG9FH19PVBMGRLV", "info": {"w": 256, "h": 256, "size": 1851129, "mimetype": "image/gif", "thumbnail_url": "mxc://matrix.gubanov.site/cCnKgi1Aze39wnxsKPG9FH19PVBMGRLV", "thumbnail_info": {"w": 256, "h": 256, "size": 1851129, "mimetype": "image/gif"}}, "msgtype": "m.sticker", "id": "tg-5395565640696236222", "net.maunium.telegram.sticker": {"pack": {"id": "7628409135175827415", "short_name": "myttcore"}, "id": "5395565640696236222", "emoticons": ["😝"]}}, {"body": "😏", "url": "mxc://matrix.gubanov.site/zggdZpNhPpS2wRfqX7K7KzTp0UTnoQ1a", "info": {"w": 256, "h": 256, "size": 4171912, "mimetype": "image/gif", "thumbnail_url": "mxc://matrix.gubanov.site/zggdZpNhPpS2wRfqX7K7KzTp0UTnoQ1a", "thumbnail_info": {"w": 256, "h": 256, "size": 4171912, "mimetype": "image/gif"}}, "msgtype": "m.sticker", "id": "tg-5267014009646776993", "net.maunium.telegram.sticker": {"pack": {"id": "7628409135175827415", "short_name": "myttcore"}, "id": "5267014009646776993", "emoticons": ["😏"]}}, {"body": "🐍", "url": "mxc://matrix.gubanov.site/ItbsRtxUmwGSPlrJgu8vXEI7KlkOJVcS", "info": {"w": 256, "h": 256, "size": 3942516, "mimetype": "image/gif", "thumbnail_url": "mxc://matrix.gubanov.site/ItbsRtxUmwGSPlrJgu8vXEI7KlkOJVcS", "thumbnail_info": {"w": 256, "h": 256, "size": 3942516, "mimetype": "image/gif"}}, "msgtype": "m.sticker", "id": "tg-5278532274416025994", "net.maunium.telegram.sticker": {"pack": {"id": "7628409135175827415", "short_name": "myttcore"}, "id": "5278532274416025994", "emoticons": ["🐍"]}}, {"body": "💩", "url": "mxc://matrix.gubanov.site/K8LXSUbg4xLMl8VrbzNT7M9KOBihHKqD", "info": {"w": 256, "h": 256, "size": 2392782, "mimetype": "image/gif", "thumbnail_url": "mxc://matrix.gubanov.site/K8LXSUbg4xLMl8VrbzNT7M9KOBihHKqD", "thumbnail_info": {"w": 256, "h": 256, "size": 2392782, "mimetype": "image/gif"}}, "msgtype": "m.sticker", "id": "tg-5267044091597722987", "net.maunium.telegram.sticker": {"pack": {"id": "7628409135175827415", "short_name": "myttcore"}, "id": "5267044091597722987", "emoticons": ["💩"]}}, {"body": "🍑", "url": "mxc://matrix.gubanov.site/KDmk4wYfj3KqLfz4JESRfic17m3FLBO5", "info": {"w": 256, "h": 256, "size": 2329073, "mimetype": "image/gif", "thumbnail_url": "mxc://matrix.gubanov.site/KDmk4wYfj3KqLfz4JESRfic17m3FLBO5", "thumbnail_info": {"w": 256, "h": 256, "size": 2329073, "mimetype": "image/gif"}}, "msgtype": "m.sticker", "id": "tg-5222233173085160292", "net.maunium.telegram.sticker": {"pack": {"id": "7628409135175827415", "short_name": "myttcore"}, "id": "5222233173085160292", "emoticons": ["🍑"]}}, {"body": "👱‍♀️", "url": "mxc://matrix.gubanov.site/rOg8DogYipFWKrGk1FjZHdLi6ium3Bwb", "info": {"w": 256, "h": 256, "size": 2045723, "mimetype": "image/gif", "thumbnail_url": "mxc://matrix.gubanov.site/rOg8DogYipFWKrGk1FjZHdLi6ium3Bwb", "thumbnail_info": {"w": 256, "h": 256, "size": 2045723, "mimetype": "image/gif"}}, "msgtype": "m.sticker", "id": "tg-5222454273706590265", "net.maunium.telegram.sticker": {"pack": {"id": "7628409135175827415", "short_name": "myttcore"}, "id": "5222454273706590265", "emoticons": ["👱‍♀"]}}, {"body": "👁", "url": "mxc://matrix.gubanov.site/zulzTKvWVtRKixZDIil4nyWy2yH6elpP", "info": {"w": 256, "h": 256, "size": 3394064, "mimetype": "image/gif", "thumbnail_url": "mxc://matrix.gubanov.site/zulzTKvWVtRKixZDIil4nyWy2yH6elpP", "thumbnail_info": {"w": 256, "h": 256, "size": 3394064, "mimetype": "image/gif"}}, "msgtype": "m.sticker", "id": "tg-5222440577055886939", "net.maunium.telegram.sticker": {"pack": {"id": "7628409135175827415", "short_name": "myttcore"}, "id": "5222440577055886939", "emoticons": ["👁"]}}, {"body": "🙏", "url": "mxc://matrix.gubanov.site/TYjIYQ35RxIkr4cQ4jZs0HrySA28oivw", "info": {"w": 256, "h": 256, "size": 3369793, "mimetype": "image/gif", "thumbnail_url": "mxc://matrix.gubanov.site/TYjIYQ35RxIkr4cQ4jZs0HrySA28oivw", "thumbnail_info": {"w": 256, "h": 256, "size": 3369793, "mimetype": "image/gif"}}, "msgtype": "m.sticker", "id": "tg-5224732646482935153", "net.maunium.telegram.sticker": {"pack": {"id": "7628409135175827415", "short_name": "myttcore"}, "id": "5224732646482935153", "emoticons": ["🙏"]}}, {"body": "🥺", "url": "mxc://matrix.gubanov.site/UtlMdqux3vvkyvVqa5NVNSaxr0gND00h", "info": {"w": 256, "h": 256, "size": 1604634, "mimetype": "image/gif", "thumbnail_url": "mxc://matrix.gubanov.site/UtlMdqux3vvkyvVqa5NVNSaxr0gND00h", "thumbnail_info": {"w": 256, "h": 256, "size": 1604634, "mimetype": "image/gif"}}, "msgtype": "m.sticker", "id": "tg-5278606392666652099", "net.maunium.telegram.sticker": {"pack": {"id": "7628409135175827415", "short_name": "myttcore"}, "id": "5278606392666652099", "emoticons": ["🥺"]}}, {"body": "🐿", "url": "mxc://matrix.gubanov.site/n15gU8qyeS31nV7taK0oQO9TDIyPNlQq", "info": {"w": 256, "h": 256, "size": 3287864, "mimetype": "image/gif", "thumbnail_url": "mxc://matrix.gubanov.site/n15gU8qyeS31nV7taK0oQO9TDIyPNlQq", "thumbnail_info": {"w": 256, "h": 256, "size": 3287864, "mimetype": "image/gif"}}, "msgtype": "m.sticker", "id": "tg-5276205480178388480", "net.maunium.telegram.sticker": {"pack": {"id": "7628409135175827415", "short_name": "myttcore"}, "id": "5276205480178388480", "emoticons": ["🐿"]}}, {"body": "🐈‍⬛", "url": "mxc://matrix.gubanov.site/MfOw9BS2LsV3jmFMDynVNVnVht21PagW", "info": {"w": 256, "h": 256, "size": 36721, "mimetype": "image/gif", "thumbnail_url": "mxc://matrix.gubanov.site/MfOw9BS2LsV3jmFMDynVNVnVht21PagW", "thumbnail_info": {"w": 256, "h": 256, "size": 36721, "mimetype": "image/gif"}}, "msgtype": "m.sticker", "id": "tg-5258154883684528095", "net.maunium.telegram.sticker": {"pack": {"id": "7628409135175827415", "short_name": "myttcore"}, "id": "5258154883684528095", "emoticons": ["🐈‍⬛"]}}, {"body": "🐈‍⬛", "url": "mxc://matrix.gubanov.site/0RprKZqQ2ia4tK0N7fLxr4txfhV3sqH2", "info": {"w": 256, "h": 256, "size": 1208281, "mimetype": "image/gif", "thumbnail_url": "mxc://matrix.gubanov.site/0RprKZqQ2ia4tK0N7fLxr4txfhV3sqH2", "thumbnail_info": {"w": 256, "h": 256, "size": 1208281, "mimetype": "image/gif"}}, "msgtype": "m.sticker", "id": "tg-5368825264505645801", "net.maunium.telegram.sticker": {"pack": {"id": "7628409135175827415", "short_name": "myttcore"}, "id": "5368825264505645801", "emoticons": ["🐈‍⬛"]}}, {"body": "🤓", "url": "mxc://matrix.gubanov.site/SZ9ErC4lwGVyvKE8jYciBzmgqXsY5V1L", "info": {"w": 256, "h": 256, "size": 48899, "mimetype": "image/gif", "thumbnail_url": "mxc://matrix.gubanov.site/SZ9ErC4lwGVyvKE8jYciBzmgqXsY5V1L", "thumbnail_info": {"w": 256, "h": 256, "size": 48899, "mimetype": "image/gif"}}, "msgtype": "m.sticker", "id": "tg-5408966574314911802", "net.maunium.telegram.sticker": {"pack": {"id": "7628409135175827415", "short_name": "myttcore"}, "id": "5408966574314911802", "emoticons": ["🤓"]}}, {"body": "😏", "url": "mxc://matrix.gubanov.site/JDCJfRSoT1DUv6fNKTs4otZvK54trJFI", "info": {"w": 256, "h": 256, "size": 974549, "mimetype": "image/gif", "thumbnail_url": "mxc://matrix.gubanov.site/JDCJfRSoT1DUv6fNKTs4otZvK54trJFI", "thumbnail_info": {"w": 256, "h": 256, "size": 974549, "mimetype": "image/gif"}}, "msgtype": "m.sticker", "id": "tg-5447519051167332306", "net.maunium.telegram.sticker": {"pack": {"id": "7628409135175827415", "short_name": "myttcore"}, "id": "5447519051167332306", "emoticons": ["😏"]}}, {"body": "🥱", "url": "mxc://matrix.gubanov.site/3keAj9n3G3l2QXryl6RUmKpNFdakgtb4", "info": {"w": 256, "h": 256, "size": 7246935, "mimetype": "image/gif", "thumbnail_url": "mxc://matrix.gubanov.site/3keAj9n3G3l2QXryl6RUmKpNFdakgtb4", "thumbnail_info": {"w": 256, "h": 256, "size": 7246935, "mimetype": "image/gif"}}, "msgtype": "m.sticker", "id": "tg-5406644581850704059", "net.maunium.telegram.sticker": {"pack": {"id": "7628409135175827415", "short_name": "myttcore"}, "id": "5406644581850704059", "emoticons": ["🥱"]}}, {"body": "🎂", "url": "mxc://matrix.gubanov.site/1O2bNdTpzK3brYtfiqgp3eOCIt0T7Hvq", "info": {"w": 256, "h": 256, "size": 2724876, "mimetype": "image/gif", "thumbnail_url": "mxc://matrix.gubanov.site/1O2bNdTpzK3brYtfiqgp3eOCIt0T7Hvq", "thumbnail_info": {"w": 256, "h": 256, "size": 2724876, "mimetype": "image/gif"}}, "msgtype": "m.sticker", "id": "tg-5276523067240121938", "net.maunium.telegram.sticker": {"pack": {"id": "7628409135175827415", "short_name": "myttcore"}, "id": "5276523067240121938", "emoticons": ["🎂"]}}, {"body": "🕷", "url": "mxc://matrix.gubanov.site/R2zBdBdE464O6PGYGOLyOw43wy1zV0Zl", "info": {"w": 256, "h": 256, "size": 17821, "mimetype": "image/gif", "thumbnail_url": "mxc://matrix.gubanov.site/R2zBdBdE464O6PGYGOLyOw43wy1zV0Zl", "thumbnail_info": {"w": 256, "h": 256, "size": 17821, "mimetype": "image/gif"}}, "msgtype": "m.sticker", "id": "tg-5474527063949992803", "net.maunium.telegram.sticker": {"pack": {"id": "7628409135175827415", "short_name": "myttcore"}, "id": "5474527063949992803", "emoticons": ["😝", "🕷"]}}, {"body": "😎", "url": "mxc://matrix.gubanov.site/ZYFIzqcyGwjTQFAqMG69w3nzDbqjj37D", "info": {"w": 256, "h": 256, "size": 45459, "mimetype": "image/gif", "thumbnail_url": "mxc://matrix.gubanov.site/ZYFIzqcyGwjTQFAqMG69w3nzDbqjj37D", "thumbnail_info": {"w": 256, "h": 256, "size": 45459, "mimetype": "image/gif"}}, "msgtype": "m.sticker", "id": "tg-5211088454506538873", "net.maunium.telegram.sticker": {"pack": {"id": "7628409135175827415", "short_name": "myttcore"}, "id": "5211088454506538873", "emoticons": ["😎"]}}, {"body": "😩", "url": "mxc://matrix.gubanov.site/IA3HWqN6xnhDNC93LpYDWxKU4NUu9ZL3", "info": {"w": 256, "h": 256, "size": 40742, "mimetype": "image/gif", "thumbnail_url": "mxc://matrix.gubanov.site/IA3HWqN6xnhDNC93LpYDWxKU4NUu9ZL3", "thumbnail_info": {"w": 256, "h": 256, "size": 40742, "mimetype": "image/gif"}}, "msgtype": "m.sticker", "id": "tg-5395431934069335643", "net.maunium.telegram.sticker": {"pack": {"id": "7628409135175827415", "short_name": "myttcore"}, "id": "5395431934069335643", "emoticons": ["😩", "😫"]}}, {"body": "😦", "url": "mxc://matrix.gubanov.site/J3cMtT8cZ8aUEn4zPpXBjK2MltJGV9Nu", "info": {"w": 256, "h": 256, "size": 31953, "mimetype": "image/gif", "thumbnail_url": "mxc://matrix.gubanov.site/J3cMtT8cZ8aUEn4zPpXBjK2MltJGV9Nu", "thumbnail_info": {"w": 256, "h": 256, "size": 31953, "mimetype": "image/gif"}}, "msgtype": "m.sticker", "id": "tg-5272021396053061672", "net.maunium.telegram.sticker": {"pack": {"id": "7628409135175827415", "short_name": "myttcore"}, "id": "5272021396053061672", "emoticons": ["😦"]}}, {"body": "😌", "url": "mxc://matrix.gubanov.site/DZkhj9bbXvU87lQvUcz8I0p9s92yirsG", "info": {"w": 256, "h": 256, "size": 33369, "mimetype": "image/gif", "thumbnail_url": "mxc://matrix.gubanov.site/DZkhj9bbXvU87lQvUcz8I0p9s92yirsG", "thumbnail_info": {"w": 256, "h": 256, "size": 33369, "mimetype": "image/gif"}}, "msgtype": "m.sticker", "id": "tg-5278621738584791263", "net.maunium.telegram.sticker": {"pack": {"id": "7628409135175827415", "short_name": "myttcore"}, "id": "5278621738584791263", "emoticons": ["😌"]}}, {"body": "🎸", "url": "mxc://matrix.gubanov.site/nqPejQ7tpbRXylESWA2zvzBrWKby2Utx", "info": {"w": 256, "h": 256, "size": 41137, "mimetype": "image/gif", "thumbnail_url": "mxc://matrix.gubanov.site/nqPejQ7tpbRXylESWA2zvzBrWKby2Utx", "thumbnail_info": {"w": 256, "h": 256, "size": 41137, "mimetype": "image/gif"}}, "msgtype": "m.sticker", "id": "tg-5283203403537738100", "net.maunium.telegram.sticker": {"pack": {"id": "7628409135175827415", "short_name": "myttcore"}, "id": "5283203403537738100", "emoticons": ["🎸"]}}, {"body": "🚬", "url": "mxc://matrix.gubanov.site/s55UgH79fn831K2M5wUUM5NT1SMw0KCe", "info": {"w": 256, "h": 256, "size": 40672, "mimetype": "image/gif", "thumbnail_url": "mxc://matrix.gubanov.site/s55UgH79fn831K2M5wUUM5NT1SMw0KCe", "thumbnail_info": {"w": 256, "h": 256, "size": 40672, "mimetype": "image/gif"}}, "msgtype": "m.sticker", "id": "tg-5359385549159292576", "net.maunium.telegram.sticker": {"pack": {"id": "7628409135175827415", "short_name": "myttcore"}, "id": "5359385549159292576", "emoticons": ["🚬"]}}, {"body": "😭", "url": "mxc://matrix.gubanov.site/agGppd5Q66dK0I72N611gqiREb6ctTgk", "info": {"w": 256, "h": 256, "size": 59767, "mimetype": "image/gif", "thumbnail_url": "mxc://matrix.gubanov.site/agGppd5Q66dK0I72N611gqiREb6ctTgk", "thumbnail_info": {"w": 256, "h": 256, "size": 59767, "mimetype": "image/gif"}}, "msgtype": "m.sticker", "id": "tg-5289740726014339140", "net.maunium.telegram.sticker": {"pack": {"id": "7628409135175827415", "short_name": "myttcore"}, "id": "5289740726014339140", "emoticons": ["😭"]}}, {"body": "😧", "url": "mxc://matrix.gubanov.site/97qwjWoY1MG1posa9hYtENxHaLJ19boP", "info": {"w": 256, "h": 256, "size": 49009, "mimetype": "image/gif", "thumbnail_url": "mxc://matrix.gubanov.site/97qwjWoY1MG1posa9hYtENxHaLJ19boP", "thumbnail_info": {"w": 256, "h": 256, "size": 49009, "mimetype": "image/gif"}}, "msgtype": "m.sticker", "id": "tg-5359741898300875897", "net.maunium.telegram.sticker": {"pack": {"id": "7628409135175827415", "short_name": "myttcore"}, "id": "5359741898300875897", "emoticons": ["😧"]}}, {"body": "😒", "url": "mxc://matrix.gubanov.site/6xB9VzMP29jJBjFOg3HCZ5RQ37m2h4F1", "info": {"w": 256, "h": 256, "size": 48285, "mimetype": "image/gif", "thumbnail_url": "mxc://matrix.gubanov.site/6xB9VzMP29jJBjFOg3HCZ5RQ37m2h4F1", "thumbnail_info": {"w": 256, "h": 256, "size": 48285, "mimetype": "image/gif"}}, "msgtype": "m.sticker", "id": "tg-5359576572124750675", "net.maunium.telegram.sticker": {"pack": {"id": "7628409135175827415", "short_name": "myttcore"}, "id": "5359576572124750675", "emoticons": ["😒"]}}, {"body": "😌", "url": "mxc://matrix.gubanov.site/5BH8G78OgDT5VJRLYYXrSnideVIOhfgr", "info": {"w": 256, "h": 256, "size": 43553, "mimetype": "image/gif", "thumbnail_url": "mxc://matrix.gubanov.site/5BH8G78OgDT5VJRLYYXrSnideVIOhfgr", "thumbnail_info": {"w": 256, "h": 256, "size": 43553, "mimetype": "image/gif"}}, "msgtype": "m.sticker", "id": "tg-5388984131596085536", "net.maunium.telegram.sticker": {"pack": {"id": "7628409135175827415", "short_name": "myttcore"}, "id": "5388984131596085536", "emoticons": ["😌"]}}, {"body": "😏", "url": "mxc://matrix.gubanov.site/C6Pa4aEs8JBtpMzCJpbKAGrySoT7rOpD", "info": {"w": 256, "h": 256, "size": 38383, "mimetype": "image/gif", "thumbnail_url": "mxc://matrix.gubanov.site/C6Pa4aEs8JBtpMzCJpbKAGrySoT7rOpD", "thumbnail_info": {"w": 256, "h": 256, "size": 38383, "mimetype": "image/gif"}}, "msgtype": "m.sticker", "id": "tg-5237859913375445617", "net.maunium.telegram.sticker": {"pack": {"id": "7628409135175827415", "short_name": "myttcore"}, "id": "5237859913375445617", "emoticons": ["😁", "😏"]}}, {"body": "😒", "url": "mxc://matrix.gubanov.site/V0EmbA2vvX1mGgVsFfDBI1Pyr0FMNMiz", "info": {"w": 256, "h": 256, "size": 39653, "mimetype": "image/gif", "thumbnail_url": "mxc://matrix.gubanov.site/V0EmbA2vvX1mGgVsFfDBI1Pyr0FMNMiz", "thumbnail_info": {"w": 256, "h": 256, "size": 39653, "mimetype": "image/gif"}}, "msgtype": "m.sticker", "id": "tg-5278591420410649855", "net.maunium.telegram.sticker": {"pack": {"id": "7628409135175827415", "short_name": "myttcore"}, "id": "5278591420410649855", "emoticons": ["😒"]}}]}